Metadata-Version: 1.0
Name: DSND-distributions
Version: 1.0
Summary: Gaussian and binomial distributions
Home-page: UNKNOWN
Author: Catherine Patino
Author-email: cnspatino@gmail.com
License: UNKNOWN
Platform: UNKNOWN
